{
  "schoolYear": "2025-2026",
  "instrumentSlug": "treble-chorus",
  "instrumentName": "Treble Choruses",
  "songCount": 1355,
  "publisherCount": 1410,
  "noteCount": 1,
  "databaseRecordCount": 1356,
  "classBreakdown": {
    "6": 22,
    "5": 206,
    "4": 268,
    "3": 374,
    "2": 307,
    "1": 178
  },
  "noMemoryRequiredCount": 0,
  "publicDomainPdfCount": 0,
  "eventBreakdown": {
    "Treble Chorus": 1355
  },
  "notes": {
    "dataset_audit": "Sourced from local CSV snapshots. Imported 2026-03-28T03:10:13.656083+00:00."
  }
}