[
  {
    "uilCode": "340-3-35649",
    "instrumentSlug": "trumpet-quartet",
    "instrumentName": "Trumpet Quartets",
    "eventName": "Trumpet Quartet",
    "title": "Two Hymns for Trumpet - Volume 1",
    "composer": "",
    "arranger": "Poor",
    "publishers": [
      "Eighth Note Publications"
    ],
    "publisherText": "Eighth Note Publications",
    "classLevel": 3,
    "specification": "",
    "noMemoryRequired": false,
    "publicDomainPdfUrl": null,
    "publicDomainSource": null
  },
  {
    "uilCode": "340-3-13680",
    "instrumentSlug": "trumpet-quartet",
    "instrumentName": "Trumpet Quartets",
    "eventName": "Trumpet Quartet",
    "title": "Deep River",
    "composer": "Anon. or Trad.",
    "arranger": "Fraker",
    "publishers": [
      "C.L. Barnhouse Company"
    ],
    "publisherText": "C.L. Barnhouse Company",
    "classLevel": 3,
    "specification": "",
    "noMemoryRequired": false,
    "publicDomainPdfUrl": null,
    "publicDomainSource": null
  },
  {
    "uilCode": "340-3-13681",
    "instrumentSlug": "trumpet-quartet",
    "instrumentName": "Trumpet Quartets",
    "eventName": "Trumpet Quartet",
    "title": "Torch Dance",
    "composer": "Anon. or Trad.",
    "arranger": "Fraker",
    "publishers": [
      "C.L. Barnhouse Company"
    ],
    "publisherText": "C.L. Barnhouse Company",
    "classLevel": 3,
    "specification": "",
    "noMemoryRequired": false,
    "publicDomainPdfUrl": null,
    "publicDomainSource": null
  },
  {
    "uilCode": "340-3-13673",
    "instrumentSlug": "trumpet-quartet",
    "instrumentName": "Trumpet Quartets",
    "eventName": "Trumpet Quartet",
    "title": "Menuet in G (from Anna Magdalena Bach Notebook)",
    "composer": "Bach",
    "arranger": "Dishinger",
    "publishers": [
      "Medici Music Press"
    ],
    "publisherText": "Medici Music Press",
    "classLevel": 3,
    "specification": "",
    "noMemoryRequired": false,
    "publicDomainPdfUrl": null,
    "publicDomainSource": null
  },
  {
    "uilCode": "340-3-13674",
    "instrumentSlug": "trumpet-quartet",
    "instrumentName": "Trumpet Quartets",
    "eventName": "Trumpet Quartet",
    "title": "Musette",
    "composer": "Bach",
    "arranger": "Dishinger",
    "publishers": [
      "Medici Music Press"
    ],
    "publisherText": "Medici Music Press",
    "classLevel": 3,
    "specification": "",
    "noMemoryRequired": false,
    "publicDomainPdfUrl": null,
    "publicDomainSource": null
  },
  {
    "uilCode": "340-3-13675",
    "instrumentSlug": "trumpet-quartet",
    "instrumentName": "Trumpet Quartets",
    "eventName": "Trumpet Quartet",
    "title": "Prelude (from Trumpet Symphony)",
    "composer": "Bizet",
    "arranger": "Holmes",
    "publishers": [
      "Rubank, Inc."
    ],
    "publisherText": "Rubank, Inc.",
    "classLevel": 3,
    "specification": "",
    "noMemoryRequired": false,
    "publicDomainPdfUrl": null,
    "publicDomainSource": null
  },
  {
    "uilCode": "340-3-13676",
    "instrumentSlug": "trumpet-quartet",
    "instrumentName": "Trumpet Quartets",
    "eventName": "Trumpet Quartet",
    "title": "Trumpet Serenade (from Quartet Repertoire)",
    "composer": "Dieterich",
    "arranger": "",
    "publishers": [
      "Rubank, Inc."
    ],
    "publisherText": "Rubank, Inc.",
    "classLevel": 3,
    "specification": "",
    "noMemoryRequired": false,
    "publicDomainPdfUrl": null,
    "publicDomainSource": null
  },
  {
    "uilCode": "340-3-13677",
    "instrumentSlug": "trumpet-quartet",
    "instrumentName": "Trumpet Quartets",
    "eventName": "Trumpet Quartet",
    "title": "Spinning Song",
    "composer": "Ellmenreich",
    "arranger": "Irons",
    "publishers": [
      "Rubank, Inc."
    ],
    "publisherText": "Rubank, Inc.",
    "classLevel": 3,
    "specification": "",
    "noMemoryRequired": false,
    "publicDomainPdfUrl": null,
    "publicDomainSource": null
  },
  {
    "uilCode": "340-3-13678",
    "instrumentSlug": "trumpet-quartet",
    "instrumentName": "Trumpet Quartets",
    "eventName": "Trumpet Quartet",
    "title": "Prelude",
    "composer": "Fitzgerald",
    "arranger": "",
    "publishers": [
      "Carl Fischer, Inc."
    ],
    "publisherText": "Carl Fischer, Inc.",
    "classLevel": 3,
    "specification": "",
    "noMemoryRequired": false,
    "publicDomainPdfUrl": null,
    "publicDomainSource": null
  },
  {
    "uilCode": "340-3-13679",
    "instrumentSlug": "trumpet-quartet",
    "instrumentName": "Trumpet Quartets",
    "eventName": "Trumpet Quartet",
    "title": "New Dawn",
    "composer": "Fraker",
    "arranger": "",
    "publishers": [
      "C.L. Barnhouse Company"
    ],
    "publisherText": "C.L. Barnhouse Company",
    "classLevel": 3,
    "specification": "",
    "noMemoryRequired": false,
    "publicDomainPdfUrl": null,
    "publicDomainSource": null
  },
  {
    "uilCode": "340-3-29922",
    "instrumentSlug": "trumpet-quartet",
    "instrumentName": "Trumpet Quartets",
    "eventName": "Trumpet Quartet",
    "title": "Festive Fanfare",
    "composer": "Giovannini",
    "arranger": "",
    "publishers": [
      "Dorabet Music Co."
    ],
    "publisherText": "Dorabet Music Co.",
    "classLevel": 3,
    "specification": "",
    "noMemoryRequired": false,
    "publicDomainPdfUrl": null,
    "publicDomainSource": null
  },
  {
    "uilCode": "340-3-13682",
    "instrumentSlug": "trumpet-quartet",
    "instrumentName": "Trumpet Quartets",
    "eventName": "Trumpet Quartet",
    "title": "Six Aufzuge",
    "composer": "Gordigiani",
    "arranger": "",
    "publishers": [
      "Ludwig Doblinger"
    ],
    "publisherText": "Ludwig Doblinger",
    "classLevel": 3,
    "specification": "(play three)",
    "noMemoryRequired": false,
    "publicDomainPdfUrl": null,
    "publicDomainSource": null
  },
  {
    "uilCode": "340-3-13683",
    "instrumentSlug": "trumpet-quartet",
    "instrumentName": "Trumpet Quartets",
    "eventName": "Trumpet Quartet",
    "title": "Allegro (from Concerto Grosso Op. 3 No. 4)",
    "composer": "Handel",
    "arranger": "Dishinger",
    "publishers": [
      "Medici Music Press"
    ],
    "publisherText": "Medici Music Press",
    "classLevel": 3,
    "specification": "",
    "noMemoryRequired": false,
    "publicDomainPdfUrl": null,
    "publicDomainSource": null
  },
  {
    "uilCode": "340-3-13684",
    "instrumentSlug": "trumpet-quartet",
    "instrumentName": "Trumpet Quartets",
    "eventName": "Trumpet Quartet",
    "title": "Nocturne (from Trumpet Symphony)",
    "composer": "Mendelssohn",
    "arranger": "Holmes",
    "publishers": [
      "Rubank, Inc."
    ],
    "publisherText": "Rubank, Inc.",
    "classLevel": 3,
    "specification": "",
    "noMemoryRequired": false,
    "publicDomainPdfUrl": null,
    "publicDomainSource": null
  },
  {
    "uilCode": "340-3-13685",
    "instrumentSlug": "trumpet-quartet",
    "instrumentName": "Trumpet Quartets",
    "eventName": "Trumpet Quartet",
    "title": "Song of the Lark (from Trumpet Symphony)",
    "composer": "Mendelssohn",
    "arranger": "Holmes",
    "publishers": [
      "Rubank, Inc."
    ],
    "publisherText": "Rubank, Inc.",
    "classLevel": 3,
    "specification": "",
    "noMemoryRequired": false,
    "publicDomainPdfUrl": null,
    "publicDomainSource": null
  },
  {
    "uilCode": "340-3-34178",
    "instrumentSlug": "trumpet-quartet",
    "instrumentName": "Trumpet Quartets",
    "eventName": "Trumpet Quartet",
    "title": "Cease Mine Eyes",
    "composer": "Morley",
    "arranger": "Chidester",
    "publishers": [
      "www.trumpetensemblemusic.com"
    ],
    "publisherText": "www.trumpetensemblemusic.com",
    "classLevel": 3,
    "specification": "",
    "noMemoryRequired": false,
    "publicDomainPdfUrl": null,
    "publicDomainSource": null
  },
  {
    "uilCode": "340-3-13686",
    "instrumentSlug": "trumpet-quartet",
    "instrumentName": "Trumpet Quartets",
    "eventName": "Trumpet Quartet",
    "title": "Baroque Suite",
    "composer": "Ostrander",
    "arranger": "",
    "publishers": [
      "Edition Musicus-New York, Inc."
    ],
    "publisherText": "Edition Musicus-New York, Inc.",
    "classLevel": 3,
    "specification": "(play mvts 1 & 2 or 2 & 3)",
    "noMemoryRequired": false,
    "publicDomainPdfUrl": null,
    "publicDomainSource": null
  },
  {
    "uilCode": "340-3-13687",
    "instrumentSlug": "trumpet-quartet",
    "instrumentName": "Trumpet Quartets",
    "eventName": "Trumpet Quartet",
    "title": "Intrada and Intermezzo (from Quartet Repertoire)",
    "composer": "Ostransky",
    "arranger": "",
    "publishers": [
      "Rubank, Inc."
    ],
    "publisherText": "Rubank, Inc.",
    "classLevel": 3,
    "specification": "",
    "noMemoryRequired": false,
    "publicDomainPdfUrl": null,
    "publicDomainSource": null
  },
  {
    "uilCode": "340-3-34177",
    "instrumentSlug": "trumpet-quartet",
    "instrumentName": "Trumpet Quartets",
    "eventName": "Trumpet Quartet",
    "title": "The Four Aces",
    "composer": "Pappas",
    "arranger": "",
    "publishers": [
      "JPM Music Publications"
    ],
    "publisherText": "JPM Music Publications",
    "classLevel": 3,
    "specification": "",
    "noMemoryRequired": false,
    "publicDomainPdfUrl": null,
    "publicDomainSource": null
  },
  {
    "uilCode": "340-3-13688",
    "instrumentSlug": "trumpet-quartet",
    "instrumentName": "Trumpet Quartets",
    "eventName": "Trumpet Quartet",
    "title": "Il Est Bel Et Bon",
    "composer": "Passereau",
    "arranger": "Reeve",
    "publishers": [
      "J&W Chester, Ltd."
    ],
    "publisherText": "J&W Chester, Ltd.",
    "classLevel": 3,
    "specification": "",
    "noMemoryRequired": false,
    "publicDomainPdfUrl": null,
    "publicDomainSource": null
  },
  {
    "uilCode": "340-3-13689",
    "instrumentSlug": "trumpet-quartet",
    "instrumentName": "Trumpet Quartets",
    "eventName": "Trumpet Quartet",
    "title": "Gavotte (from Harpsichord Suite No. 5)",
    "composer": "Purcell",
    "arranger": "Vedeski",
    "publishers": [
      "Medici Music Press"
    ],
    "publisherText": "Medici Music Press",
    "classLevel": 3,
    "specification": "",
    "noMemoryRequired": false,
    "publicDomainPdfUrl": null,
    "publicDomainSource": null
  },
  {
    "uilCode": "340-3-13690",
    "instrumentSlug": "trumpet-quartet",
    "instrumentName": "Trumpet Quartets",
    "eventName": "Trumpet Quartet",
    "title": "In These Delightful Pleasant Groves",
    "composer": "Purcell",
    "arranger": "Kaisershot",
    "publishers": [
      "Kendor Music, Inc."
    ],
    "publisherText": "Kendor Music, Inc.",
    "classLevel": 3,
    "specification": "",
    "noMemoryRequired": false,
    "publicDomainPdfUrl": null,
    "publicDomainSource": null
  },
  {
    "uilCode": "340-3-13691",
    "instrumentSlug": "trumpet-quartet",
    "instrumentName": "Trumpet Quartets",
    "eventName": "Trumpet Quartet",
    "title": "Rigaudon (from Pieces de Clavecin, 1724)",
    "composer": "Rameau",
    "arranger": "Dishinger",
    "publishers": [
      "Medici Music Press"
    ],
    "publisherText": "Medici Music Press",
    "classLevel": 3,
    "specification": "",
    "noMemoryRequired": false,
    "publicDomainPdfUrl": null,
    "publicDomainSource": null
  },
  {
    "uilCode": "340-3-35648",
    "instrumentSlug": "trumpet-quartet",
    "instrumentName": "Trumpet Quartets",
    "eventName": "Trumpet Quartet",
    "title": "Abendgang im Lenz",
    "composer": "Reger",
    "arranger": "Chidester",
    "publishers": [
      "www.trumpetensemblemusic.com"
    ],
    "publisherText": "www.trumpetensemblemusic.com",
    "classLevel": 3,
    "specification": "",
    "noMemoryRequired": false,
    "publicDomainPdfUrl": null,
    "publicDomainSource": null
  },
  {
    "uilCode": "340-3-13692",
    "instrumentSlug": "trumpet-quartet",
    "instrumentName": "Trumpet Quartets",
    "eventName": "Trumpet Quartet",
    "title": "Marche Militaire",
    "composer": "Schubert",
    "arranger": "Lotzenhiser",
    "publishers": [
      "Belwin, Inc"
    ],
    "publisherText": "Belwin, Inc",
    "classLevel": 3,
    "specification": "",
    "noMemoryRequired": false,
    "publicDomainPdfUrl": null,
    "publicDomainSource": null
  },
  {
    "uilCode": "340-3-29925",
    "instrumentSlug": "trumpet-quartet",
    "instrumentName": "Trumpet Quartets",
    "eventName": "Trumpet Quartet",
    "title": "Festival Fanfare #3",
    "composer": "Uber",
    "arranger": "",
    "publishers": [
      "Kendor Music, Inc."
    ],
    "publisherText": "Kendor Music, Inc.",
    "classLevel": 3,
    "specification": "",
    "noMemoryRequired": false,
    "publicDomainPdfUrl": null,
    "publicDomainSource": null
  },
  {
    "uilCode": "340-3-13694",
    "instrumentSlug": "trumpet-quartet",
    "instrumentName": "Trumpet Quartets",
    "eventName": "Trumpet Quartet",
    "title": "The Cricket",
    "composer": "Vecchi",
    "arranger": "Maganini",
    "publishers": [
      "Edition Musicus-New York, Inc."
    ],
    "publisherText": "Edition Musicus-New York, Inc.",
    "classLevel": 3,
    "specification": "",
    "noMemoryRequired": false,
    "publicDomainPdfUrl": null,
    "publicDomainSource": null
  },
  {
    "uilCode": "340-3-13695",
    "instrumentSlug": "trumpet-quartet",
    "instrumentName": "Trumpet Quartets",
    "eventName": "Trumpet Quartet",
    "title": "Triumphal March (from Trumpet Symphony)",
    "composer": "Verdi",
    "arranger": "Holmes",
    "publishers": [
      "Rubank, Inc."
    ],
    "publisherText": "Rubank, Inc.",
    "classLevel": 3,
    "specification": "",
    "noMemoryRequired": false,
    "publicDomainPdfUrl": null,
    "publicDomainSource": null
  },
  {
    "uilCode": "340-3-13696",
    "instrumentSlug": "trumpet-quartet",
    "instrumentName": "Trumpet Quartets",
    "eventName": "Trumpet Quartet",
    "title": "Hunter's Chorus (from Trumpet Symphony)",
    "composer": "von Weber",
    "arranger": "Holmes",
    "publishers": [
      "Rubank, Inc."
    ],
    "publisherText": "Rubank, Inc.",
    "classLevel": 3,
    "specification": "",
    "noMemoryRequired": false,
    "publicDomainPdfUrl": null,
    "publicDomainSource": null
  },
  {
    "uilCode": "340-3-13697",
    "instrumentSlug": "trumpet-quartet",
    "instrumentName": "Trumpet Quartets",
    "eventName": "Trumpet Quartet",
    "title": "Leise, Leise (from Quartet Repertoire)",
    "composer": "von Weber",
    "arranger": "Irons",
    "publishers": [
      "Rubank, Inc."
    ],
    "publisherText": "Rubank, Inc.",
    "classLevel": 3,
    "specification": "",
    "noMemoryRequired": false,
    "publicDomainPdfUrl": null,
    "publicDomainSource": null
  },
  {
    "uilCode": "340-2-35647",
    "instrumentSlug": "trumpet-quartet",
    "instrumentName": "Trumpet Quartets",
    "eventName": "Trumpet Quartet",
    "title": "Three for Four",
    "composer": "",
    "arranger": "",
    "publishers": [
      "Tripolo Press"
    ],
    "publisherText": "Tripolo Press",
    "classLevel": 2,
    "specification": "(play two mvts)",
    "noMemoryRequired": false,
    "publicDomainPdfUrl": null,
    "publicDomainSource": null
  },
  {
    "uilCode": "340-2-13651",
    "instrumentSlug": "trumpet-quartet",
    "instrumentName": "Trumpet Quartets",
    "eventName": "Trumpet Quartet",
    "title": "Kyrie in F",
    "composer": "Bach",
    "arranger": "Dishinger",
    "publishers": [
      "Medici Music Press"
    ],
    "publisherText": "Medici Music Press",
    "classLevel": 2,
    "specification": "",
    "noMemoryRequired": false,
    "publicDomainPdfUrl": null,
    "publicDomainSource": null
  },
  {
    "uilCode": "340-2-13652",
    "instrumentSlug": "trumpet-quartet",
    "instrumentName": "Trumpet Quartets",
    "eventName": "Trumpet Quartet",
    "title": "Kyrie in G",
    "composer": "Bach",
    "arranger": "Dishinger",
    "publishers": [
      "Medici Music Press"
    ],
    "publisherText": "Medici Music Press",
    "classLevel": 2,
    "specification": "",
    "noMemoryRequired": false,
    "publicDomainPdfUrl": null,
    "publicDomainSource": null
  },
  {
    "uilCode": "340-2-25370",
    "instrumentSlug": "trumpet-quartet",
    "instrumentName": "Trumpet Quartets",
    "eventName": "Trumpet Quartet",
    "title": "Sarabande and Double",
    "composer": "Bach",
    "arranger": "Brom",
    "publishers": [
      "Kendor Music, Inc."
    ],
    "publisherText": "Kendor Music, Inc.",
    "classLevel": 2,
    "specification": "",
    "noMemoryRequired": false,
    "publicDomainPdfUrl": null,
    "publicDomainSource": null
  },
  {
    "uilCode": "340-2-13653",
    "instrumentSlug": "trumpet-quartet",
    "instrumentName": "Trumpet Quartets",
    "eventName": "Trumpet Quartet",
    "title": "Rowland",
    "composer": "Byrd",
    "arranger": "Dishinger",
    "publishers": [
      "Medici Music Press"
    ],
    "publisherText": "Medici Music Press",
    "classLevel": 2,
    "specification": "(no repeats)",
    "noMemoryRequired": false,
    "publicDomainPdfUrl": null,
    "publicDomainSource": null
  },
  {
    "uilCode": "340-2-13654",
    "instrumentSlug": "trumpet-quartet",
    "instrumentName": "Trumpet Quartets",
    "eventName": "Trumpet Quartet",
    "title": "The Earle of Oxford's Marche",
    "composer": "Byrd",
    "arranger": "Dishinger",
    "publishers": [
      "Medici Music Press"
    ],
    "publisherText": "Medici Music Press",
    "classLevel": 2,
    "specification": "",
    "noMemoryRequired": false,
    "publicDomainPdfUrl": null,
    "publicDomainSource": null
  },
  {
    "uilCode": "340-2-13656",
    "instrumentSlug": "trumpet-quartet",
    "instrumentName": "Trumpet Quartets",
    "eventName": "Trumpet Quartet",
    "title": "March and Chorale",
    "composer": "Dillon",
    "arranger": "",
    "publishers": [
      "Boosey & Hawkes, Inc."
    ],
    "publisherText": "Boosey & Hawkes, Inc.",
    "classLevel": 2,
    "specification": "",
    "noMemoryRequired": false,
    "publicDomainPdfUrl": null,
    "publicDomainSource": null
  },
  {
    "uilCode": "340-2-13657",
    "instrumentSlug": "trumpet-quartet",
    "instrumentName": "Trumpet Quartets",
    "eventName": "Trumpet Quartet",
    "title": "Americana Suite No.1",
    "composer": "Dishinger",
    "arranger": "",
    "publishers": [
      "Medici Music Press"
    ],
    "publisherText": "Medici Music Press",
    "classLevel": 2,
    "specification": "(play mvts 1 & 3 or 1 & 4 or 2 & 3 or 2 & 4)",
    "noMemoryRequired": false,
    "publicDomainPdfUrl": null,
    "publicDomainSource": null
  },
  {
    "uilCode": "340-2-13658",
    "instrumentSlug": "trumpet-quartet",
    "instrumentName": "Trumpet Quartets",
    "eventName": "Trumpet Quartet",
    "title": "English Madrigal Suite",
    "composer": "Farmer",
    "arranger": "Dishinger",
    "publishers": [
      "Medici Music Press"
    ],
    "publisherText": "Medici Music Press",
    "classLevel": 2,
    "specification": "(play mvt 1)",
    "noMemoryRequired": false,
    "publicDomainPdfUrl": null,
    "publicDomainSource": null
  },
  {
    "uilCode": "340-2-13659",
    "instrumentSlug": "trumpet-quartet",
    "instrumentName": "Trumpet Quartets",
    "eventName": "Trumpet Quartet",
    "title": "Madrigal: Io Pur Respiro",
    "composer": "Gesualdo",
    "arranger": "Dishinger",
    "publishers": [
      "Medici Music Press"
    ],
    "publisherText": "Medici Music Press",
    "classLevel": 2,
    "specification": "",
    "noMemoryRequired": false,
    "publicDomainPdfUrl": null,
    "publicDomainSource": null
  },
  {
    "uilCode": "340-2-29923",
    "instrumentSlug": "trumpet-quartet",
    "instrumentName": "Trumpet Quartets",
    "eventName": "Trumpet Quartet",
    "title": "Hornpipe (from Water Music)",
    "composer": "Handel",
    "arranger": "Conley",
    "publishers": [
      "Kendor Music, Inc."
    ],
    "publisherText": "Kendor Music, Inc.",
    "classLevel": 2,
    "specification": "",
    "noMemoryRequired": false,
    "publicDomainPdfUrl": null,
    "publicDomainSource": null
  },
  {
    "uilCode": "340-2-35644",
    "instrumentSlug": "trumpet-quartet",
    "instrumentName": "Trumpet Quartets",
    "eventName": "Trumpet Quartet",
    "title": "Quartet No. 1 in A Minor",
    "composer": "Haspiel",
    "arranger": "",
    "publishers": [
      "JPM Music Publications"
    ],
    "publisherText": "JPM Music Publications",
    "classLevel": 2,
    "specification": "",
    "noMemoryRequired": false,
    "publicDomainPdfUrl": null,
    "publicDomainSource": null
  },
  {
    "uilCode": "340-2-35645",
    "instrumentSlug": "trumpet-quartet",
    "instrumentName": "Trumpet Quartets",
    "eventName": "Trumpet Quartet",
    "title": "Quartet No. 2 in G Minor",
    "composer": "Haspiel",
    "arranger": "",
    "publishers": [
      "JPM Music Publications"
    ],
    "publisherText": "JPM Music Publications",
    "classLevel": 2,
    "specification": "",
    "noMemoryRequired": false,
    "publicDomainPdfUrl": null,
    "publicDomainSource": null
  },
  {
    "uilCode": "340-2-35646",
    "instrumentSlug": "trumpet-quartet",
    "instrumentName": "Trumpet Quartets",
    "eventName": "Trumpet Quartet",
    "title": "Three Nordic Quartets",
    "composer": "H\u00f8rven",
    "arranger": "Olcott",
    "publishers": [
      "Tripolo Press"
    ],
    "publisherText": "Tripolo Press",
    "classLevel": 2,
    "specification": "(play two mvts)",
    "noMemoryRequired": false,
    "publicDomainPdfUrl": null,
    "publicDomainSource": null
  },
  {
    "uilCode": "340-2-13660",
    "instrumentSlug": "trumpet-quartet",
    "instrumentName": "Trumpet Quartets",
    "eventName": "Trumpet Quartet",
    "title": "Sonata da Chiesa",
    "composer": "Israel",
    "arranger": "",
    "publishers": [
      "Theodore Presser Company"
    ],
    "publisherText": "Theodore Presser Company",
    "classLevel": 2,
    "specification": "(play two mvts)",
    "noMemoryRequired": false,
    "publicDomainPdfUrl": null,
    "publicDomainSource": null
  },
  {
    "uilCode": "340-2-13661",
    "instrumentSlug": "trumpet-quartet",
    "instrumentName": "Trumpet Quartets",
    "eventName": "Trumpet Quartet",
    "title": "The Game",
    "composer": "Kabalevsky",
    "arranger": "Lester",
    "publishers": [
      "JTL Publications, G. Scott Music Publishing Co."
    ],
    "publisherText": "JTL Publications, G. Scott Music Publishing Co.",
    "classLevel": 2,
    "specification": "(play all)",
    "noMemoryRequired": false,
    "publicDomainPdfUrl": null,
    "publicDomainSource": null
  },
  {
    "uilCode": "340-2-13662",
    "instrumentSlug": "trumpet-quartet",
    "instrumentName": "Trumpet Quartets",
    "eventName": "Trumpet Quartet",
    "title": "Moods",
    "composer": "Leonard",
    "arranger": "",
    "publishers": [
      "H.T. FitzSimons Company"
    ],
    "publisherText": "H.T. FitzSimons Company",
    "classLevel": 2,
    "specification": "",
    "noMemoryRequired": false,
    "publicDomainPdfUrl": null,
    "publicDomainSource": null
  },
  {
    "uilCode": "340-2-13663",
    "instrumentSlug": "trumpet-quartet",
    "instrumentName": "Trumpet Quartets",
    "eventName": "Trumpet Quartet",
    "title": "Marcia Grandioso",
    "composer": "Lotzenhiser",
    "arranger": "",
    "publishers": [
      "Rubank, Inc."
    ],
    "publisherText": "Rubank, Inc.",
    "classLevel": 2,
    "specification": "",
    "noMemoryRequired": false,
    "publicDomainPdfUrl": null,
    "publicDomainSource": null
  },
  {
    "uilCode": "340-2-13664",
    "instrumentSlug": "trumpet-quartet",
    "instrumentName": "Trumpet Quartets",
    "eventName": "Trumpet Quartet",
    "title": "Scherzetto",
    "composer": "Lotzenhiser",
    "arranger": "",
    "publishers": [
      "Rubank, Inc."
    ],
    "publisherText": "Rubank, Inc.",
    "classLevel": 2,
    "specification": "",
    "noMemoryRequired": false,
    "publicDomainPdfUrl": null,
    "publicDomainSource": null
  },
  {
    "uilCode": "340-2-13665",
    "instrumentSlug": "trumpet-quartet",
    "instrumentName": "Trumpet Quartets",
    "eventName": "Trumpet Quartet",
    "title": "Canzona (from Canzoni a 4 Voci)",
    "composer": "Maschera",
    "arranger": "Dishinger",
    "publishers": [
      "Medici Music Press"
    ],
    "publisherText": "Medici Music Press",
    "classLevel": 2,
    "specification": "",
    "noMemoryRequired": false,
    "publicDomainPdfUrl": null,
    "publicDomainSource": null
  },
  {
    "uilCode": "340-2-13666",
    "instrumentSlug": "trumpet-quartet",
    "instrumentName": "Trumpet Quartets",
    "eventName": "Trumpet Quartet",
    "title": "American Panorama",
    "composer": "McKay",
    "arranger": "",
    "publishers": [
      "Carl Fischer, Inc."
    ],
    "publisherText": "Carl Fischer, Inc.",
    "classLevel": 2,
    "specification": "(play two)",
    "noMemoryRequired": false,
    "publicDomainPdfUrl": null,
    "publicDomainSource": null
  },
  {
    "uilCode": "340-2-35642",
    "instrumentSlug": "trumpet-quartet",
    "instrumentName": "Trumpet Quartets",
    "eventName": "Trumpet Quartet",
    "title": "Eine Kleine Nachtmusik",
    "composer": "Mozart",
    "arranger": "Ziek",
    "publishers": [
      "Kendor Music, Inc."
    ],
    "publisherText": "Kendor Music, Inc.",
    "classLevel": 2,
    "specification": "",
    "noMemoryRequired": false,
    "publicDomainPdfUrl": null,
    "publicDomainSource": null
  },
  {
    "uilCode": "340-2-13667",
    "instrumentSlug": "trumpet-quartet",
    "instrumentName": "Trumpet Quartets",
    "eventName": "Trumpet Quartet",
    "title": "Fanfare and Allegro",
    "composer": "Ostransky",
    "arranger": "",
    "publishers": [
      "Rubank, Inc."
    ],
    "publisherText": "Rubank, Inc.",
    "classLevel": 2,
    "specification": "",
    "noMemoryRequired": false,
    "publicDomainPdfUrl": null,
    "publicDomainSource": null
  },
  {
    "uilCode": "340-2-13668",
    "instrumentSlug": "trumpet-quartet",
    "instrumentName": "Trumpet Quartets",
    "eventName": "Trumpet Quartet",
    "title": "Pavane and Canzonetta",
    "composer": "Ostransky",
    "arranger": "",
    "publishers": [
      "Rubank, Inc."
    ],
    "publisherText": "Rubank, Inc.",
    "classLevel": 2,
    "specification": "",
    "noMemoryRequired": false,
    "publicDomainPdfUrl": null,
    "publicDomainSource": null
  },
  {
    "uilCode": "340-2-35643",
    "instrumentSlug": "trumpet-quartet",
    "instrumentName": "Trumpet Quartets",
    "eventName": "Trumpet Quartet",
    "title": "Equinox",
    "composer": "Pethel",
    "arranger": "",
    "publishers": [
      "Tripolo Press"
    ],
    "publisherText": "Tripolo Press",
    "classLevel": 2,
    "specification": "",
    "noMemoryRequired": false,
    "publicDomainPdfUrl": null,
    "publicDomainSource": null
  },
  {
    "uilCode": "340-2-13669",
    "instrumentSlug": "trumpet-quartet",
    "instrumentName": "Trumpet Quartets",
    "eventName": "Trumpet Quartet",
    "title": "Marche (from Suite No. 5 for Clavier)",
    "composer": "Purcell",
    "arranger": "Dishinger",
    "publishers": [
      "Medici Music Press"
    ],
    "publisherText": "Medici Music Press",
    "classLevel": 2,
    "specification": "",
    "noMemoryRequired": false,
    "publicDomainPdfUrl": null,
    "publicDomainSource": null
  },
  {
    "uilCode": "340-2-13670",
    "instrumentSlug": "trumpet-quartet",
    "instrumentName": "Trumpet Quartets",
    "eventName": "Trumpet Quartet",
    "title": "Two Ceremonial Classics",
    "composer": "Purcell",
    "arranger": "Campbell",
    "publishers": [
      "Kendor Music, Inc."
    ],
    "publisherText": "Kendor Music, Inc.",
    "classLevel": 2,
    "specification": "",
    "noMemoryRequired": false,
    "publicDomainPdfUrl": null,
    "publicDomainSource": null
  },
  {
    "uilCode": "340-2-13671",
    "instrumentSlug": "trumpet-quartet",
    "instrumentName": "Trumpet Quartets",
    "eventName": "Trumpet Quartet",
    "title": "Sonatina for Four Trumpets",
    "composer": "Simpson",
    "arranger": "",
    "publishers": [
      "Carl Fischer, Inc."
    ],
    "publisherText": "Carl Fischer, Inc.",
    "classLevel": 2,
    "specification": "",
    "noMemoryRequired": false,
    "publicDomainPdfUrl": null,
    "publicDomainSource": null
  },
  {
    "uilCode": "340-2-29924",
    "instrumentSlug": "trumpet-quartet",
    "instrumentName": "Trumpet Quartets",
    "eventName": "Trumpet Quartet",
    "title": "Trepak (from The Nutcracker Suite)",
    "composer": "Tchaikovsky",
    "arranger": "Kaisershot",
    "publishers": [
      "Kendor Music, Inc."
    ],
    "publisherText": "Kendor Music, Inc.",
    "classLevel": 2,
    "specification": "",
    "noMemoryRequired": false,
    "publicDomainPdfUrl": null,
    "publicDomainSource": null
  },
  {
    "uilCode": "340-2-13693",
    "instrumentSlug": "trumpet-quartet",
    "instrumentName": "Trumpet Quartets",
    "eventName": "Trumpet Quartet",
    "title": "Toccata",
    "composer": "Telemann",
    "arranger": "Schmidt",
    "publishers": [
      "Western International Music, Inc."
    ],
    "publisherText": "Western International Music, Inc.",
    "classLevel": 2,
    "specification": "",
    "noMemoryRequired": false,
    "publicDomainPdfUrl": null,
    "publicDomainSource": null
  },
  {
    "uilCode": "340-2-35641",
    "instrumentSlug": "trumpet-quartet",
    "instrumentName": "Trumpet Quartets",
    "eventName": "Trumpet Quartet",
    "title": "Coral Reef",
    "composer": "Thompson",
    "arranger": "",
    "publishers": [
      "Eighth Note Publications"
    ],
    "publisherText": "Eighth Note Publications",
    "classLevel": 2,
    "specification": "",
    "noMemoryRequired": false,
    "publicDomainPdfUrl": null,
    "publicDomainSource": null
  },
  {
    "uilCode": "340-2-13672",
    "instrumentSlug": "trumpet-quartet",
    "instrumentName": "Trumpet Quartets",
    "eventName": "Trumpet Quartet",
    "title": "Fanfare and Processional",
    "composer": "Turini",
    "arranger": "Weinandt",
    "publishers": [
      "Southern Music Company"
    ],
    "publisherText": "Southern Music Company",
    "classLevel": 2,
    "specification": "(play one)",
    "noMemoryRequired": false,
    "publicDomainPdfUrl": null,
    "publicDomainSource": null
  },
  {
    "uilCode": "340-2-13655",
    "instrumentSlug": "trumpet-quartet",
    "instrumentName": "Trumpet Quartets",
    "eventName": "Trumpet Quartet",
    "title": "Two Renaissance Canons",
    "composer": "des Pres",
    "arranger": "Decker",
    "publishers": [
      "Medici Music Press"
    ],
    "publisherText": "Medici Music Press",
    "classLevel": 2,
    "specification": "",
    "noMemoryRequired": false,
    "publicDomainPdfUrl": null,
    "publicDomainSource": null
  },
  {
    "uilCode": "340-1-29920",
    "instrumentSlug": "trumpet-quartet",
    "instrumentName": "Trumpet Quartets",
    "eventName": "Trumpet Quartet",
    "title": "Dos Tiempos",
    "composer": "Ackley",
    "arranger": "",
    "publishers": [
      "Cimarron Music Press"
    ],
    "publisherText": "Cimarron Music Press",
    "classLevel": 1,
    "specification": "",
    "noMemoryRequired": false,
    "publicDomainPdfUrl": null,
    "publicDomainSource": null
  },
  {
    "uilCode": "340-1-13645",
    "instrumentSlug": "trumpet-quartet",
    "instrumentName": "Trumpet Quartets",
    "eventName": "Trumpet Quartet",
    "title": "Baroque Suite",
    "composer": "Anon. or Trad.",
    "arranger": "Ostrander",
    "publishers": [
      "Qunito Maganini"
    ],
    "publisherText": "Qunito Maganini",
    "classLevel": 1,
    "specification": "",
    "noMemoryRequired": false,
    "publicDomainPdfUrl": null,
    "publicDomainSource": null
  },
  {
    "uilCode": "340-1-13635",
    "instrumentSlug": "trumpet-quartet",
    "instrumentName": "Trumpet Quartets",
    "eventName": "Trumpet Quartet",
    "title": "Six Marcie per la Cavalleria",
    "composer": "Anon. or Trad.",
    "arranger": "Blumel",
    "publishers": [
      "Tezak Edition"
    ],
    "publisherText": "Tezak Edition",
    "classLevel": 1,
    "specification": "",
    "noMemoryRequired": false,
    "publicDomainPdfUrl": null,
    "publicDomainSource": null
  },
  {
    "uilCode": "340-1-13633",
    "instrumentSlug": "trumpet-quartet",
    "instrumentName": "Trumpet Quartets",
    "eventName": "Trumpet Quartet",
    "title": "Jesu, Joy of Man's Desiring",
    "composer": "Bach",
    "arranger": "Thurston",
    "publishers": [
      "Southern Music Company"
    ],
    "publisherText": "Southern Music Company",
    "classLevel": 1,
    "specification": "",
    "noMemoryRequired": false,
    "publicDomainPdfUrl": null,
    "publicDomainSource": null
  },
  {
    "uilCode": "340-1-13634",
    "instrumentSlug": "trumpet-quartet",
    "instrumentName": "Trumpet Quartets",
    "eventName": "Trumpet Quartet",
    "title": "Tournament of Trumpets",
    "composer": "Bennett",
    "arranger": "",
    "publishers": [
      "Carl Fischer, Inc."
    ],
    "publisherText": "Carl Fischer, Inc.",
    "classLevel": 1,
    "specification": "",
    "noMemoryRequired": false,
    "publicDomainPdfUrl": null,
    "publicDomainSource": null
  },
  {
    "uilCode": "340-1-13636",
    "instrumentSlug": "trumpet-quartet",
    "instrumentName": "Trumpet Quartets",
    "eventName": "Trumpet Quartet",
    "title": "Country Pictures",
    "composer": "Brandt",
    "arranger": "",
    "publishers": [
      "International Music Company"
    ],
    "publisherText": "International Music Company",
    "classLevel": 1,
    "specification": "",
    "noMemoryRequired": false,
    "publicDomainPdfUrl": null,
    "publicDomainSource": null
  },
  {
    "uilCode": "340-1-13637",
    "instrumentSlug": "trumpet-quartet",
    "instrumentName": "Trumpet Quartets",
    "eventName": "Trumpet Quartet",
    "title": "Four Fanfares for all Occasions",
    "composer": "Bush",
    "arranger": "",
    "publishers": [
      "Wimbledon Music, Inc."
    ],
    "publisherText": "Wimbledon Music, Inc.",
    "classLevel": 1,
    "specification": "(play three)",
    "noMemoryRequired": false,
    "publicDomainPdfUrl": null,
    "publicDomainSource": null
  },
  {
    "uilCode": "340-1-34179",
    "instrumentSlug": "trumpet-quartet",
    "instrumentName": "Trumpet Quartets",
    "eventName": "Trumpet Quartet",
    "title": "Clarke Technical Studies (1 - 5)",
    "composer": "Clarke",
    "arranger": "Chidester",
    "publishers": [
      "www.trumpetensemblemusic.com"
    ],
    "publisherText": "www.trumpetensemblemusic.com",
    "classLevel": 1,
    "specification": "(play No. 2 only)",
    "noMemoryRequired": false,
    "publicDomainPdfUrl": null,
    "publicDomainSource": null
  },
  {
    "uilCode": "340-1-13638",
    "instrumentSlug": "trumpet-quartet",
    "instrumentName": "Trumpet Quartets",
    "eventName": "Trumpet Quartet",
    "title": "Six Pieces D'Audition",
    "composer": "Defaye",
    "arranger": "",
    "publishers": [
      "Alphonse Leduc"
    ],
    "publisherText": "Alphonse Leduc",
    "classLevel": 1,
    "specification": "(play mvt 5 or 6)",
    "noMemoryRequired": false,
    "publicDomainPdfUrl": null,
    "publicDomainSource": null
  },
  {
    "uilCode": "340-1-13639",
    "instrumentSlug": "trumpet-quartet",
    "instrumentName": "Trumpet Quartets",
    "eventName": "Trumpet Quartet",
    "title": "Baroque Suite",
    "composer": "Dishinger",
    "arranger": "",
    "publishers": [
      "Medici Music Press"
    ],
    "publisherText": "Medici Music Press",
    "classLevel": 1,
    "specification": "(play three or more mvts)",
    "noMemoryRequired": false,
    "publicDomainPdfUrl": null,
    "publicDomainSource": null
  },
  {
    "uilCode": "340-1-13640",
    "instrumentSlug": "trumpet-quartet",
    "instrumentName": "Trumpet Quartets",
    "eventName": "Trumpet Quartet",
    "title": "Suite for Trumpets",
    "composer": "Dubensky",
    "arranger": "",
    "publishers": [
      "Charles Colin Music Publishers"
    ],
    "publisherText": "Charles Colin Music Publishers",
    "classLevel": 1,
    "specification": "(play mvts 1 & 2 or mvt 3)",
    "noMemoryRequired": false,
    "publicDomainPdfUrl": null,
    "publicDomainSource": null
  },
  {
    "uilCode": "340-1-13641",
    "instrumentSlug": "trumpet-quartet",
    "instrumentName": "Trumpet Quartets",
    "eventName": "Trumpet Quartet",
    "title": "Scherzino",
    "composer": "Fitzgerald",
    "arranger": "",
    "publishers": [
      "Carl Fischer, Inc."
    ],
    "publisherText": "Carl Fischer, Inc.",
    "classLevel": 1,
    "specification": "",
    "noMemoryRequired": false,
    "publicDomainPdfUrl": null,
    "publicDomainSource": null
  },
  {
    "uilCode": "340-1-13642",
    "instrumentSlug": "trumpet-quartet",
    "instrumentName": "Trumpet Quartets",
    "eventName": "Trumpet Quartet",
    "title": "The Rushin' Trumpeters",
    "composer": "Gillis",
    "arranger": "",
    "publishers": [
      "Belwin, Inc"
    ],
    "publisherText": "Belwin, Inc",
    "classLevel": 1,
    "specification": "",
    "noMemoryRequired": false,
    "publicDomainPdfUrl": null,
    "publicDomainSource": null
  },
  {
    "uilCode": "340-1-35640",
    "instrumentSlug": "trumpet-quartet",
    "instrumentName": "Trumpet Quartets",
    "eventName": "Trumpet Quartet",
    "title": "Three Nordic Quartets",
    "composer": "H\u00f8rven",
    "arranger": "Olcott",
    "publishers": [
      "Tripolo Press"
    ],
    "publisherText": "Tripolo Press",
    "classLevel": 1,
    "specification": "",
    "noMemoryRequired": false,
    "publicDomainPdfUrl": null,
    "publicDomainSource": null
  },
  {
    "uilCode": "340-1-38603",
    "instrumentSlug": "trumpet-quartet",
    "instrumentName": "Trumpet Quartets",
    "eventName": "Trumpet Quartet",
    "title": "Sonata con Trombe",
    "composer": "Jacchini",
    "arranger": "Chidester",
    "publishers": [
      "www.trumpetensemblemusic.com"
    ],
    "publisherText": "www.trumpetensemblemusic.com",
    "classLevel": 1,
    "specification": "(piano accomp REQUIRED)",
    "noMemoryRequired": false,
    "publicDomainPdfUrl": null,
    "publicDomainSource": null
  },
  {
    "uilCode": "340-1-13643",
    "instrumentSlug": "trumpet-quartet",
    "instrumentName": "Trumpet Quartets",
    "eventName": "Trumpet Quartet",
    "title": "Festival Prelude",
    "composer": "Johnson",
    "arranger": "",
    "publishers": [
      "Belwin, Inc"
    ],
    "publisherText": "Belwin, Inc",
    "classLevel": 1,
    "specification": "",
    "noMemoryRequired": false,
    "publicDomainPdfUrl": null,
    "publicDomainSource": null
  },
  {
    "uilCode": "340-1-13644",
    "instrumentSlug": "trumpet-quartet",
    "instrumentName": "Trumpet Quartets",
    "eventName": "Trumpet Quartet",
    "title": "Three Elizabethan Madrigals",
    "composer": "Kaisershot",
    "arranger": "",
    "publishers": [
      "Kendor Music, Inc."
    ],
    "publisherText": "Kendor Music, Inc.",
    "classLevel": 1,
    "specification": "",
    "noMemoryRequired": false,
    "publicDomainPdfUrl": null,
    "publicDomainSource": null
  },
  {
    "uilCode": "340-1-35639",
    "instrumentSlug": "trumpet-quartet",
    "instrumentName": "Trumpet Quartets",
    "eventName": "Trumpet Quartet",
    "title": "Three For Four",
    "composer": "Olcott",
    "arranger": "",
    "publishers": [
      "Tripolo Press"
    ],
    "publisherText": "Tripolo Press",
    "classLevel": 1,
    "specification": "",
    "noMemoryRequired": false,
    "publicDomainPdfUrl": null,
    "publicDomainSource": null
  },
  {
    "uilCode": "340-1-13646",
    "instrumentSlug": "trumpet-quartet",
    "instrumentName": "Trumpet Quartets",
    "eventName": "Trumpet Quartet",
    "title": "Four Trump",
    "composer": "Rugolo",
    "arranger": "",
    "publishers": [
      "RBC Publications"
    ],
    "publisherText": "RBC Publications",
    "classLevel": 1,
    "specification": "",
    "noMemoryRequired": false,
    "publicDomainPdfUrl": null,
    "publicDomainSource": null
  },
  {
    "uilCode": "340-1-13647",
    "instrumentSlug": "trumpet-quartet",
    "instrumentName": "Trumpet Quartets",
    "eventName": "Trumpet Quartet",
    "title": "Canzon",
    "composer": "Scheidt",
    "arranger": "",
    "publishers": [
      "Robert King"
    ],
    "publisherText": "Robert King",
    "classLevel": 1,
    "specification": "",
    "noMemoryRequired": false,
    "publicDomainPdfUrl": null,
    "publicDomainSource": null
  },
  {
    "uilCode": "340-1-13648",
    "instrumentSlug": "trumpet-quartet",
    "instrumentName": "Trumpet Quartets",
    "eventName": "Trumpet Quartet",
    "title": "Canzon Cornetto",
    "composer": "Scheidt",
    "arranger": "",
    "publishers": [
      "J&W Chester, Ltd."
    ],
    "publisherText": "J&W Chester, Ltd.",
    "classLevel": 1,
    "specification": "",
    "noMemoryRequired": false,
    "publicDomainPdfUrl": null,
    "publicDomainSource": null
  },
  {
    "uilCode": "340-1-13649",
    "instrumentSlug": "trumpet-quartet",
    "instrumentName": "Trumpet Quartets",
    "eventName": "Trumpet Quartet",
    "title": "Concerto for Four Trumpets",
    "composer": "Telemann",
    "arranger": "Nagel",
    "publishers": [
      "Mentor Music, Inc."
    ],
    "publisherText": "Mentor Music, Inc.",
    "classLevel": 1,
    "specification": "(play mvts 1 & 2 or 1 & 4)",
    "noMemoryRequired": false,
    "publicDomainPdfUrl": null,
    "publicDomainSource": null
  },
  {
    "uilCode": "340-1-35638",
    "instrumentSlug": "trumpet-quartet",
    "instrumentName": "Trumpet Quartets",
    "eventName": "Trumpet Quartet",
    "title": "Telemann Suite",
    "composer": "Telemann",
    "arranger": "Bjornes",
    "publishers": [
      "Tripolo Press"
    ],
    "publisherText": "Tripolo Press",
    "classLevel": 1,
    "specification": "(play three mvts)",
    "noMemoryRequired": false,
    "publicDomainPdfUrl": null,
    "publicDomainSource": null
  },
  {
    "uilCode": "340-1-13650",
    "instrumentSlug": "trumpet-quartet",
    "instrumentName": "Trumpet Quartets",
    "eventName": "Trumpet Quartet",
    "title": "Canonical Trilogy",
    "composer": "Tull",
    "arranger": "",
    "publishers": [
      "Western International Music, Inc."
    ],
    "publisherText": "Western International Music, Inc.",
    "classLevel": 1,
    "specification": "",
    "noMemoryRequired": false,
    "publicDomainPdfUrl": null,
    "publicDomainSource": null
  },
  {
    "uilCode": "340-1-25371",
    "instrumentSlug": "trumpet-quartet",
    "instrumentName": "Trumpet Quartets",
    "eventName": "Trumpet Quartet",
    "title": "Choral: Komm, Gott Schopfer, Heiliger",
    "composer": "Walter",
    "arranger": "Hickman",
    "publishers": [
      "Trigram Music Inc."
    ],
    "publisherText": "Trigram Music Inc.",
    "classLevel": 1,
    "specification": "",
    "noMemoryRequired": false,
    "publicDomainPdfUrl": null,
    "publicDomainSource": null
  }
]