{
  "444-1-17422": {
    "lastAttempted": "2026-03-28T14:41:08.770187+00:00",
    "matched": false
  },
  "444-1-17423": {
    "lastAttempted": "2026-03-28T14:41:04.393954+00:00",
    "matched": false
  },
  "444-1-17424": {
    "lastAttempted": "2026-03-28T14:40:58.140707+00:00",
    "matched": false
  },
  "444-1-17425": {
    "lastAttempted": "2026-03-28T14:41:12.634785+00:00",
    "matched": false
  },
  "444-1-17427": {
    "lastAttempted": "2026-03-28T14:41:08.189455+00:00",
    "matched": true,
    "source": "JW Pepper link"
  },
  "444-1-17429": {
    "lastAttempted": "2026-03-28T14:41:04.616908+00:00",
    "matched": false
  },
  "444-1-17430": {
    "lastAttempted": "2026-03-28T14:40:58.978783+00:00",
    "matched": true,
    "source": "JW Pepper link"
  },
  "444-1-17431": {
    "lastAttempted": "2026-03-28T14:41:04.060117+00:00",
    "matched": false
  },
  "444-1-17433": {
    "lastAttempted": "2026-03-28T14:41:05.281814+00:00",
    "matched": false
  },
  "444-1-29971": {
    "lastAttempted": "2026-03-28T14:41:00.270307+00:00",
    "matched": true,
    "source": "JW Pepper link"
  },
  "444-1-29972": {
    "lastAttempted": "2026-03-28T14:41:02.164741+00:00",
    "matched": false
  },
  "444-1-29973": {
    "lastAttempted": "2026-03-28T14:40:56.558130+00:00",
    "matched": true,
    "source": "JW Pepper link"
  },
  "444-1-30597": {
    "lastAttempted": "2026-03-28T14:41:01.055124+00:00",
    "matched": true,
    "source": "JW Pepper link"
  },
  "444-1-30598": {
    "lastAttempted": "2026-03-28T14:41:01.965133+00:00",
    "matched": false
  },
  "444-1-30599": {
    "lastAttempted": "2026-03-28T14:41:01.380118+00:00",
    "matched": true,
    "source": "JW Pepper link"
  },
  "444-1-30600": {
    "lastAttempted": "2026-03-28T14:40:59.067455+00:00",
    "matched": false
  },
  "444-1-30601": {
    "lastAttempted": "2026-03-28T14:41:02.512800+00:00",
    "matched": true,
    "source": "JW Pepper link"
  },
  "444-1-30602": {
    "lastAttempted": "2026-03-28T14:41:08.421303+00:00",
    "matched": true,
    "source": "JW Pepper link"
  },
  "444-1-30603": {
    "lastAttempted": "2026-03-28T14:41:07.895912+00:00",
    "matched": false
  },
  "444-1-30604": {
    "lastAttempted": "2026-03-28T14:41:07.576272+00:00",
    "matched": false
  },
  "444-1-30605": {
    "lastAttempted": "2026-03-28T14:41:02.550228+00:00",
    "matched": true,
    "source": "JW Pepper link"
  },
  "444-1-30606": {
    "lastAttempted": "2026-03-28T14:41:07.967069+00:00",
    "matched": true,
    "source": "JW Pepper link"
  },
  "444-1-30607": {
    "lastAttempted": "2026-03-28T14:41:09.686577+00:00",
    "matched": true,
    "source": "JW Pepper link"
  },
  "444-1-30609": {
    "lastAttempted": "2026-03-28T14:41:02.408818+00:00",
    "matched": false
  },
  "444-1-30610": {
    "lastAttempted": "2026-03-28T14:41:02.701853+00:00",
    "matched": true,
    "source": "JW Pepper link"
  },
  "444-1-30611": {
    "lastAttempted": "2026-03-28T14:41:03.931111+00:00",
    "matched": true,
    "source": "JW Pepper link"
  },
  "444-1-30612": {
    "lastAttempted": "2026-03-28T14:41:03.933110+00:00",
    "matched": true,
    "source": "JW Pepper link"
  },
  "444-1-30620": {
    "lastAttempted": "2026-03-28T14:41:08.338662+00:00",
    "matched": false
  },
  "444-1-31914": {
    "lastAttempted": "2026-03-28T14:41:07.145024+00:00",
    "matched": false
  },
  "444-1-31915": {
    "lastAttempted": "2026-03-28T14:40:59.621907+00:00",
    "matched": true,
    "source": "JW Pepper link"
  },
  "444-1-31916": {
    "lastAttempted": "2026-03-28T14:41:02.732094+00:00",
    "matched": false
  },
  "444-1-31917": {
    "lastAttempted": "2026-03-28T14:40:53.993174+00:00",
    "matched": true,
    "source": "JW Pepper link"
  },
  "444-1-32802": {
    "lastAttempted": "2026-03-28T14:41:08.862806+00:00",
    "matched": true,
    "source": "JW Pepper link"
  },
  "444-1-33772": {
    "lastAttempted": "2026-03-28T14:41:10.034555+00:00",
    "matched": true,
    "source": "JW Pepper link"
  },
  "444-1-37641": {
    "lastAttempted": "2026-03-28T14:40:58.212340+00:00",
    "matched": true,
    "source": "JW Pepper link"
  },
  "444-1-37661": {
    "lastAttempted": "2026-03-28T14:41:05.318100+00:00",
    "matched": false
  },
  "444-1-37662": {
    "lastAttempted": "2026-03-28T14:41:04.954605+00:00",
    "matched": true,
    "source": "JW Pepper link"
  },
  "444-1-37663": {
    "lastAttempted": "2026-03-28T14:41:04.749490+00:00",
    "matched": false
  },
  "444-1-37664": {
    "lastAttempted": "2026-03-28T14:41:10.000555+00:00",
    "matched": true,
    "source": "JW Pepper link"
  },
  "444-1-37665": {
    "lastAttempted": "2026-03-28T14:41:04.503076+00:00",
    "matched": true,
    "source": "JW Pepper link"
  },
  "444-1-37666": {
    "lastAttempted": "2026-03-28T14:41:05.346994+00:00",
    "matched": false
  },
  "444-1-37667": {
    "lastAttempted": "2026-03-28T14:41:10.425798+00:00",
    "matched": false
  },
  "444-1-37668": {
    "lastAttempted": "2026-03-28T14:41:05.805163+00:00",
    "matched": false
  },
  "444-1-37669": {
    "lastAttempted": "2026-03-28T14:41:05.744376+00:00",
    "matched": false
  },
  "444-1-37670": {
    "lastAttempted": "2026-03-28T14:41:06.501690+00:00",
    "matched": false
  },
  "444-1-37671": {
    "lastAttempted": "2026-03-28T14:41:05.581033+00:00",
    "matched": false
  },
  "444-1-37672": {
    "lastAttempted": "2026-03-28T14:41:08.209555+00:00",
    "matched": true,
    "source": "JW Pepper link"
  },
  "444-1-37673": {
    "lastAttempted": "2026-03-28T14:41:08.178451+00:00",
    "matched": false
  },
  "444-1-37674": {
    "lastAttempted": "2026-03-28T14:41:06.444509+00:00",
    "matched": false
  },
  "444-1-37675": {
    "lastAttempted": "2026-03-28T14:41:08.308887+00:00",
    "matched": false
  },
  "444-1-37676": {
    "lastAttempted": "2026-03-28T14:41:08.480111+00:00",
    "matched": false
  },
  "444-1-37677": {
    "lastAttempted": "2026-03-28T14:41:06.626352+00:00",
    "matched": false
  },
  "444-1-37678": {
    "lastAttempted": "2026-03-28T14:41:01.778586+00:00",
    "matched": true,
    "source": "JW Pepper link"
  },
  "444-1-37679": {
    "lastAttempted": "2026-03-28T14:41:08.044011+00:00",
    "matched": false
  },
  "444-1-37680": {
    "lastAttempted": "2026-03-28T14:41:07.750521+00:00",
    "matched": false
  },
  "444-1-37681": {
    "lastAttempted": "2026-03-28T14:41:02.799634+00:00",
    "matched": true,
    "source": "JW Pepper link"
  },
  "444-1-37682": {
    "lastAttempted": "2026-03-28T14:41:08.003548+00:00",
    "matched": false
  },
  "444-1-37683": {
    "lastAttempted": "2026-03-28T14:41:06.774839+00:00",
    "matched": false
  },
  "444-1-40636": {
    "lastAttempted": "2026-03-28T14:41:08.080341+00:00",
    "matched": false
  },
  "444-1-40637": {
    "lastAttempted": "2026-03-28T14:40:52.990019+00:00",
    "matched": true,
    "source": "JW Pepper link"
  },
  "444-1-40638": {
    "lastAttempted": "2026-03-28T14:41:06.169843+00:00",
    "matched": false
  },
  "444-1-40639": {
    "lastAttempted": "2026-03-28T14:41:06.045479+00:00",
    "matched": false
  },
  "444-1-40640": {
    "lastAttempted": "2026-03-28T14:41:06.953839+00:00",
    "matched": false
  },
  "444-1-40641": {
    "lastAttempted": "2026-03-28T14:41:02.716719+00:00",
    "matched": false
  },
  "444-1-40642": {
    "lastAttempted": "2026-03-28T14:41:02.232932+00:00",
    "matched": false
  },
  "444-1-40643": {
    "lastAttempted": "2026-03-28T14:41:22.258544+00:00",
    "matched": false
  },
  "444-1-40644": {
    "lastAttempted": "2026-03-28T14:41:03.692609+00:00",
    "matched": true,
    "source": "JW Pepper link"
  },
  "444-1-40645": {
    "lastAttempted": "2026-03-28T14:41:03.320295+00:00",
    "matched": true,
    "source": "JW Pepper link"
  },
  "444-1-40646": {
    "lastAttempted": "2026-03-28T14:41:03.770712+00:00",
    "matched": false
  },
  "444-1-40647": {
    "lastAttempted": "2026-03-28T14:41:11.273010+00:00",
    "matched": false
  },
  "444-1-40648": {
    "lastAttempted": "2026-03-28T14:41:10.066528+00:00",
    "matched": false
  },
  "444-1-40649": {
    "lastAttempted": "2026-03-28T14:41:15.301450+00:00",
    "matched": false
  },
  "444-1-40650": {
    "lastAttempted": "2026-03-28T14:41:15.381438+00:00",
    "matched": true,
    "source": "JW Pepper link"
  },
  "444-1-40651": {
    "lastAttempted": "2026-03-28T14:41:23.972420+00:00",
    "matched": false
  },
  "444-1-40652": {
    "lastAttempted": "2026-03-28T14:41:15.125271+00:00",
    "matched": true,
    "source": "JW Pepper link"
  },
  "444-1-40653": {
    "lastAttempted": "2026-03-28T14:41:14.644182+00:00",
    "matched": true,
    "source": "JW Pepper link"
  },
  "444-1-40654": {
    "lastAttempted": "2026-03-28T14:41:10.148616+00:00",
    "matched": false
  },
  "444-1-40655": {
    "lastAttempted": "2026-03-28T14:41:10.954002+00:00",
    "matched": true,
    "source": "JW Pepper link"
  },
  "444-1-40656": {
    "lastAttempted": "2026-03-28T14:41:14.873714+00:00",
    "matched": true,
    "source": "JW Pepper link"
  },
  "444-1-40658": {
    "lastAttempted": "2026-03-28T14:41:15.548782+00:00",
    "matched": false
  },
  "444-1-40659": {
    "lastAttempted": "2026-03-28T14:41:29.083771+00:00",
    "matched": false
  },
  "444-1-40660": {
    "lastAttempted": "2026-03-28T14:41:30.787398+00:00",
    "matched": true,
    "source": "JW Pepper link"
  },
  "444-1-40661": {
    "lastAttempted": "2026-03-28T14:41:22.647810+00:00",
    "matched": true,
    "source": "JW Pepper link"
  },
  "444-1-40662": {
    "lastAttempted": "2026-03-28T14:41:15.542773+00:00",
    "matched": false
  },
  "444-1-40663": {
    "lastAttempted": "2026-03-28T14:41:06.565177+00:00",
    "matched": true,
    "source": "JW Pepper link"
  },
  "444-1-40664": {
    "lastAttempted": "2026-03-28T14:41:12.174299+00:00",
    "matched": false
  },
  "444-1-40665": {
    "lastAttempted": "2026-03-28T14:41:11.266795+00:00",
    "matched": false
  },
  "444-1-40666": {
    "lastAttempted": "2026-03-28T14:41:10.940212+00:00",
    "matched": false
  },
  "444-1-40667": {
    "lastAttempted": "2026-03-28T14:41:17.983780+00:00",
    "matched": true,
    "source": "JW Pepper link"
  },
  "444-1-40668": {
    "lastAttempted": "2026-03-28T14:41:07.270288+00:00",
    "matched": true,
    "source": "JW Pepper link"
  },
  "444-1-40669": {
    "lastAttempted": "2026-03-28T14:41:12.932481+00:00",
    "matched": false
  },
  "444-1-40670": {
    "lastAttempted": "2026-03-28T14:41:11.644765+00:00",
    "matched": false
  },
  "444-1-40671": {
    "lastAttempted": "2026-03-28T14:41:06.927806+00:00",
    "matched": true,
    "source": "JW Pepper link"
  },
  "444-1-40672": {
    "lastAttempted": "2026-03-28T14:41:17.910786+00:00",
    "matched": true,
    "source": "JW Pepper link"
  },
  "444-1-40673": {
    "lastAttempted": "2026-03-28T14:41:14.205850+00:00",
    "matched": false
  },
  "444-1-40674": {
    "lastAttempted": "2026-03-28T14:41:26.587766+00:00",
    "matched": true,
    "source": "JW Pepper link"
  },
  "444-1-40675": {
    "lastAttempted": "2026-03-28T14:41:22.810480+00:00",
    "matched": true,
    "source": "JW Pepper link"
  },
  "444-1-40676": {
    "lastAttempted": "2026-03-28T14:41:07.435376+00:00",
    "matched": false
  },
  "444-1-40790": {
    "lastAttempted": "2026-03-28T14:41:17.672618+00:00",
    "matched": false
  },
  "444-1-40791": {
    "lastAttempted": "2026-03-28T14:41:17.873231+00:00",
    "matched": true,
    "source": "JW Pepper link"
  },
  "444-1-40792": {
    "lastAttempted": "2026-03-28T14:41:26.070007+00:00",
    "matched": true,
    "source": "JW Pepper link"
  },
  "444-2-17421": {
    "lastAttempted": "2026-03-28T14:41:08.236202+00:00",
    "matched": false
  },
  "444-2-17435": {
    "lastAttempted": "2026-03-28T14:41:04.034480+00:00",
    "matched": false
  },
  "444-2-17437": {
    "lastAttempted": "2026-03-28T14:41:15.756182+00:00",
    "matched": true,
    "source": "JW Pepper link"
  },
  "444-2-17438": {
    "lastAttempted": "2026-03-28T14:41:04.976870+00:00",
    "matched": false
  },
  "444-2-17439": {
    "lastAttempted": "2026-03-28T14:41:03.074716+00:00",
    "matched": false
  },
  "444-2-17440": {
    "lastAttempted": "2026-03-28T14:41:03.836575+00:00",
    "matched": false
  },
  "444-2-30613": {
    "lastAttempted": "2026-03-28T14:41:04.146603+00:00",
    "matched": false
  },
  "444-2-30614": {
    "lastAttempted": "2026-03-28T14:41:04.686544+00:00",
    "matched": false
  },
  "444-2-30615": {
    "lastAttempted": "2026-03-28T14:41:03.199972+00:00",
    "matched": false
  },
  "444-2-32844": {
    "lastAttempted": "2026-03-28T14:41:04.169727+00:00",
    "matched": true,
    "source": "JW Pepper link"
  },
  "444-2-37684": {
    "lastAttempted": "2026-03-28T14:41:13.712220+00:00",
    "matched": true,
    "source": "JW Pepper link"
  },
  "444-2-37685": {
    "lastAttempted": "2026-03-28T14:41:07.902096+00:00",
    "matched": false
  },
  "444-2-37686": {
    "lastAttempted": "2026-03-28T14:41:08.410002+00:00",
    "matched": false
  },
  "444-2-37687": {
    "lastAttempted": "2026-03-28T14:41:08.835472+00:00",
    "matched": false
  },
  "444-2-37688": {
    "lastAttempted": "2026-03-28T14:41:08.361439+00:00",
    "matched": false
  },
  "444-2-37689": {
    "lastAttempted": "2026-03-28T14:41:08.694426+00:00",
    "matched": false
  },
  "444-2-40677": {
    "lastAttempted": "2026-03-28T14:41:24.791854+00:00",
    "matched": false
  },
  "444-2-40678": {
    "lastAttempted": "2026-03-28T14:41:18.658772+00:00",
    "matched": true,
    "source": "JW Pepper link"
  },
  "444-2-40679": {
    "lastAttempted": "2026-03-28T14:41:17.758756+00:00",
    "matched": true,
    "source": "JW Pepper link"
  },
  "444-2-40680": {
    "lastAttempted": "2026-03-28T14:41:14.666046+00:00",
    "matched": false
  },
  "444-2-40681": {
    "lastAttempted": "2026-03-28T14:41:20.316702+00:00",
    "matched": true,
    "source": "JW Pepper link"
  },
  "444-2-40682": {
    "lastAttempted": "2026-03-28T14:41:12.680709+00:00",
    "matched": false
  },
  "444-2-40683": {
    "lastAttempted": "2026-03-28T14:41:20.984854+00:00",
    "matched": true,
    "source": "JW Pepper link"
  },
  "444-2-40684": {
    "lastAttempted": "2026-03-28T14:41:14.530226+00:00",
    "matched": true,
    "source": "JW Pepper link"
  },
  "444-2-40685": {
    "lastAttempted": "2026-03-28T14:41:19.937851+00:00",
    "matched": false
  },
  "444-2-40686": {
    "lastAttempted": "2026-03-28T14:41:18.199948+00:00",
    "matched": false
  },
  "444-2-40687": {
    "lastAttempted": "2026-03-28T14:41:14.720571+00:00",
    "matched": true,
    "source": "JW Pepper link"
  },
  "444-2-40688": {
    "lastAttempted": "2026-03-28T14:41:19.671916+00:00",
    "matched": false
  },
  "444-2-40689": {
    "lastAttempted": "2026-03-28T14:41:19.252479+00:00",
    "matched": true,
    "source": "JW Pepper link"
  },
  "444-2-40690": {
    "lastAttempted": "2026-03-28T14:41:14.103521+00:00",
    "matched": false
  },
  "444-2-40691": {
    "lastAttempted": "2026-03-28T14:41:27.472116+00:00",
    "matched": false
  },
  "444-2-40692": {
    "lastAttempted": "2026-03-28T14:41:10.067006+00:00",
    "matched": false
  },
  "444-2-40693": {
    "lastAttempted": "2026-03-28T14:41:15.629754+00:00",
    "matched": false
  },
  "444-2-40694": {
    "lastAttempted": "2026-03-28T14:41:12.952241+00:00",
    "matched": false
  },
  "444-2-40695": {
    "lastAttempted": "2026-03-28T14:41:21.568570+00:00",
    "matched": false
  },
  "444-2-40696": {
    "lastAttempted": "2026-03-28T14:41:17.478758+00:00",
    "matched": false
  },
  "444-2-40697": {
    "lastAttempted": "2026-03-28T14:41:15.188387+00:00",
    "matched": true,
    "source": "JW Pepper link"
  },
  "444-2-40698": {
    "lastAttempted": "2026-03-28T14:41:17.642322+00:00",
    "matched": false
  },
  "444-2-40793": {
    "lastAttempted": "2026-03-28T14:41:23.478639+00:00",
    "matched": true,
    "source": "JW Pepper link"
  },
  "444-2-40794": {
    "lastAttempted": "2026-03-28T14:41:24.668194+00:00",
    "matched": false
  },
  "444-2-40795": {
    "lastAttempted": "2026-03-28T14:41:18.366420+00:00",
    "matched": false
  },
  "444-2-40796": {
    "lastAttempted": "2026-03-28T14:41:19.241255+00:00",
    "matched": false
  },
  "444-2-40797": {
    "lastAttempted": "2026-03-28T14:41:15.550957+00:00",
    "matched": true,
    "source": "JW Pepper link"
  },
  "444-2-40798": {
    "lastAttempted": "2026-03-28T14:41:21.238822+00:00",
    "matched": false
  },
  "444-2-40799": {
    "lastAttempted": "2026-03-28T14:41:27.133212+00:00",
    "matched": false
  },
  "444-2-40800": {
    "lastAttempted": "2026-03-28T14:41:35.788147+00:00",
    "matched": false
  },
  "444-3-17441": {
    "lastAttempted": "2026-03-28T14:40:53.999513+00:00",
    "matched": true,
    "source": "JW Pepper link"
  },
  "444-3-17442": {
    "lastAttempted": "2026-03-28T14:40:59.660777+00:00",
    "matched": false
  },
  "444-3-17443": {
    "lastAttempted": "2026-03-28T14:41:00.156015+00:00",
    "matched": false
  },
  "444-3-17444": {
    "lastAttempted": "2026-03-28T14:41:09.458854+00:00",
    "matched": true,
    "source": "JW Pepper link"
  },
  "444-3-17445": {
    "lastAttempted": "2026-03-28T14:41:05.610426+00:00",
    "matched": false
  },
  "444-3-17446": {
    "lastAttempted": "2026-03-28T14:41:01.022053+00:00",
    "matched": false
  },
  "444-3-17447": {
    "lastAttempted": "2026-03-28T14:41:01.080290+00:00",
    "matched": false
  },
  "444-3-30616": {
    "lastAttempted": "2026-03-28T14:41:04.608201+00:00",
    "matched": false
  },
  "444-3-30617": {
    "lastAttempted": "2026-03-28T14:41:04.785206+00:00",
    "matched": false
  },
  "444-3-30618": {
    "lastAttempted": "2026-03-28T14:41:10.018754+00:00",
    "matched": false
  },
  "444-3-32847": {
    "lastAttempted": "2026-03-28T14:41:04.658080+00:00",
    "matched": false
  },
  "444-3-37690": {
    "lastAttempted": "2026-03-28T14:41:08.910645+00:00",
    "matched": false
  },
  "444-3-37691": {
    "lastAttempted": "2026-03-28T14:41:13.191940+00:00",
    "matched": false
  },
  "444-3-37692": {
    "lastAttempted": "2026-03-28T14:41:08.062909+00:00",
    "matched": false
  },
  "444-3-40699": {
    "lastAttempted": "2026-03-28T14:41:21.378914+00:00",
    "matched": false
  },
  "444-3-40700": {
    "lastAttempted": "2026-03-28T14:41:12.486664+00:00",
    "matched": true,
    "source": "JW Pepper link"
  },
  "444-3-40701": {
    "lastAttempted": "2026-03-28T14:41:23.462776+00:00",
    "matched": false
  },
  "444-3-40702": {
    "lastAttempted": "2026-03-28T14:41:18.772690+00:00",
    "matched": false
  },
  "444-3-40801": {
    "lastAttempted": "2026-03-28T14:41:38.226678+00:00",
    "matched": false
  }
}