{
  "179-1-20655": {
    "url": "https://www.jwpepper.com/margot-labourez-les-vignes-1323443/p",
    "label": "Buy Sheet Music",
    "source": "JW Pepper link",
    "lastChecked": "2026-03-28T14:56:08.296018+00:00"
  },
  "179-1-20658": {
    "url": "https://www.jwpepper.com/ad-un-dolce-usignolo-1205426/p",
    "label": "Buy Sheet Music",
    "source": "JW Pepper link",
    "lastChecked": "2026-03-28T14:56:09.506594+00:00"
  },
  "179-1-20659": {
    "url": "https://www.jwpepper.com/contrapunto-bestiale-10707216e/p",
    "label": "Buy Sheet Music",
    "source": "JW Pepper link",
    "lastChecked": "2026-03-28T14:55:34.187343+00:00"
  },
  "179-1-20692": {
    "url": "https://www.jwpepper.com/chi-la-gagliarda-4101853/p",
    "label": "Buy Sheet Music",
    "source": "JW Pepper link",
    "lastChecked": "2026-03-28T14:56:00.099769+00:00"
  },
  "179-1-20704": {
    "url": "https://www.jwpepper.com/ein-fauler-baum-1409770/p",
    "label": "Buy Sheet Music",
    "source": "JW Pepper link",
    "lastChecked": "2026-03-28T14:56:01.604397+00:00"
  },
  "179-1-20707": {
    "url": "https://www.jwpepper.com/my-bonny-lass-she-smileth-11615760/p",
    "label": "Buy Sheet Music",
    "source": "JW Pepper link",
    "lastChecked": "2026-03-28T14:55:08.563339+00:00"
  },
  "179-1-20710": {
    "url": "https://www.jwpepper.com/coletta-ronde-villageoise-10819812/p",
    "label": "Buy Sheet Music",
    "source": "JW Pepper link",
    "lastChecked": "2026-03-28T14:55:25.897152+00:00"
  },
  "179-1-20721": {
    "url": "https://www.jwpepper.com/tanzen-und-springen-11673989/p",
    "label": "Buy Sheet Music",
    "source": "JW Pepper link",
    "lastChecked": "2026-03-28T14:56:09.966607+00:00"
  },
  "179-1-20723": {
    "url": "https://www.jwpepper.com/au-joli-jeu-1816388/p",
    "label": "Buy Sheet Music",
    "source": "JW Pepper link",
    "lastChecked": "2026-03-28T14:55:58.127469+00:00"
  },
  "179-1-20728": {
    "url": "https://www.jwpepper.com/revecy-venir-du-printans-3300201/p",
    "label": "Buy Sheet Music",
    "source": "JW Pepper link",
    "lastChecked": "2026-03-28T14:55:56.361712+00:00"
  },
  "179-1-20732": {
    "url": "https://www.jwpepper.com/european-madrigals-437855/p",
    "label": "Buy Sheet Music",
    "source": "JW Pepper link",
    "lastChecked": "2026-03-28T15:03:08.049307+00:00"
  },
  "179-1-20740": {
    "url": "https://www.jwpepper.com/dainty-fine-sweet-nymph-1382647/p",
    "label": "Buy Sheet Music",
    "source": "JW Pepper link",
    "lastChecked": "2026-03-28T14:55:29.171116+00:00"
  },
  "179-1-20741": {
    "url": "https://www.jwpepper.com/fire-fire-3251857/p",
    "label": "Buy Sheet Music",
    "source": "JW Pepper link",
    "lastChecked": "2026-03-28T14:55:33.227466+00:00"
  },
  "179-1-20744": {
    "url": "https://www.jwpepper.com/european-madrigals-437947/p",
    "label": "Buy Sheet Music",
    "source": "JW Pepper link",
    "lastChecked": "2026-03-28T14:54:35.606618+00:00"
  },
  "179-1-20746": {
    "url": "https://www.jwpepper.com/my-bonny-lass-1379940/p",
    "label": "Buy Sheet Music",
    "source": "JW Pepper link",
    "lastChecked": "2026-03-28T14:56:08.283021+00:00"
  },
  "179-1-20752": {
    "url": "https://www.jwpepper.com/two-morley-madrigals-for-men-10308715/p",
    "label": "Buy Sheet Music",
    "source": "JW Pepper link",
    "lastChecked": "2026-03-28T14:55:38.030899+00:00"
  },
  "179-1-20763": {
    "url": "https://www.jwpepper.com/in-these-delightful-pleasant-groves-340836/p",
    "label": "Buy Sheet Music",
    "source": "JW Pepper link",
    "lastChecked": "2026-03-28T14:55:55.729551+00:00"
  },
  "179-1-20769": {
    "url": "https://www.jwpepper.com/european-madrigals-437947/p",
    "label": "Buy Sheet Music",
    "source": "JW Pepper link",
    "lastChecked": "2026-03-28T14:55:37.419114+00:00"
  },
  "179-1-20773": {
    "url": "https://www.jwpepper.com/au-joli-bois-6001325/p",
    "label": "Buy Sheet Music",
    "source": "JW Pepper link",
    "lastChecked": "2026-03-28T14:54:54.535147+00:00"
  },
  "179-1-20777": {
    "url": "https://www.jwpepper.com/ah-sweet-whose-beauty-5792122/p",
    "label": "Buy Sheet Music",
    "source": "JW Pepper link",
    "lastChecked": "2026-03-28T14:55:26.912540+00:00"
  },
  "179-1-20780": {
    "url": "https://www.jwpepper.com/sweet-suffolk-owl-11657057f/p",
    "label": "Buy Sheet Music",
    "source": "JW Pepper link",
    "lastChecked": "2026-03-28T14:59:41.848998+00:00"
  },
  "179-1-20781": {
    "url": "https://www.jwpepper.com/il-bianco-e-dolce-cigno-11209020/p",
    "label": "Buy Sheet Music",
    "source": "JW Pepper link",
    "lastChecked": "2026-03-28T14:55:30.725941+00:00"
  },
  "179-1-20784": {
    "url": "https://www.jwpepper.com/lady-your-eye-my-love-enforced-5537592/p",
    "label": "Buy Sheet Music",
    "source": "JW Pepper link",
    "lastChecked": "2026-03-28T14:54:44.177036+00:00"
  },
  "179-1-20786": {
    "url": "https://www.jwpepper.com/six-weelkes-madrigals-11409083/p",
    "label": "Buy Sheet Music",
    "source": "JW Pepper link",
    "lastChecked": "2026-03-28T14:59:30.828458+00:00"
  },
  "179-1-20787": {
    "url": "https://www.jwpepper.com/wohlauf-ihr-gaste-3305082/p",
    "label": "Buy Sheet Music",
    "source": "JW Pepper link",
    "lastChecked": "2026-03-28T14:55:37.118636+00:00"
  },
  "179-1-20796": {
    "url": "https://www.jwpepper.com/sweet-honey-sucking-bees-4989398/p",
    "label": "Buy Sheet Music",
    "source": "JW Pepper link",
    "lastChecked": "2026-03-28T14:55:52.691646+00:00"
  },
  "179-1-27404": {
    "url": "https://www.jwpepper.com/vezzosi-augelli-4827127/p",
    "label": "Buy Sheet Music",
    "source": "JW Pepper link",
    "lastChecked": "2026-03-28T14:55:07.275432+00:00"
  },
  "179-1-27415": {
    "url": "https://www.jwpepper.com/douze-melodies-voice-pf-7913676/p",
    "label": "Buy Sheet Music",
    "source": "JW Pepper link",
    "lastChecked": "2026-03-28T14:56:00.804796+00:00"
  },
  "179-1-27416": {
    "url": "https://www.jwpepper.com/cantava-la-piu-vaga-pastorella-3179934/p",
    "label": "Buy Sheet Music",
    "source": "JW Pepper link",
    "lastChecked": "2026-03-28T14:55:38.171084+00:00"
  },
  "179-1-27427": {
    "url": "https://www.jwpepper.com/two-renaissance-madrigal-laments-3295011/p",
    "label": "Buy Sheet Music",
    "source": "JW Pepper link",
    "lastChecked": "2026-03-28T14:55:49.853184+00:00"
  },
  "179-1-27433": {
    "url": "https://www.jwpepper.com/the-oxford-book-of-english-madrigals-1481571/p",
    "label": "Buy Sheet Music",
    "source": "JW Pepper link",
    "lastChecked": "2026-03-28T14:56:10.628638+00:00"
  },
  "179-1-31631": {
    "url": "https://www.jwpepper.com/scaldava-il-sol-1205350/p",
    "label": "Buy Sheet Music",
    "source": "JW Pepper link",
    "lastChecked": "2026-03-28T14:55:56.694416+00:00"
  },
  "179-1-31637": {
    "url": "https://www.jwpepper.com/heraclitus-11639569e/p",
    "label": "Buy Sheet Music",
    "source": "JW Pepper link",
    "lastChecked": "2026-03-28T14:59:29.608650+00:00"
  },
  "179-1-33323": {
    "url": "https://www.jwpepper.com/my-bonny-lass-she-smileth-10760350/p",
    "label": "Buy Sheet Music",
    "source": "JW Pepper link",
    "lastChecked": "2026-03-28T14:58:57.346667+00:00"
  },
  "179-1-34224": {
    "url": "https://www.jwpepper.com/oy-es-dia-de-placer-10067354/p",
    "label": "Buy Sheet Music",
    "source": "JW Pepper link",
    "lastChecked": "2026-03-28T14:54:18.107053+00:00"
  },
  "179-1-34225": {
    "url": "https://www.jwpepper.com/now-is-the-month-of-maying-3104122/p",
    "label": "Buy Sheet Music",
    "source": "JW Pepper link",
    "lastChecked": "2026-03-28T14:54:15.292484+00:00"
  },
  "179-1-34229": {
    "url": "https://www.jwpepper.com/vita-de-la-mia-vita-3050697/p",
    "label": "Buy Sheet Music",
    "source": "JW Pepper link",
    "lastChecked": "2026-03-28T14:59:15.109066+00:00"
  },
  "179-2-20799": {
    "url": "https://www.jwpepper.com/pase-el-agoa-ma-julieta-1814912/p",
    "label": "Buy Sheet Music",
    "source": "JW Pepper link",
    "lastChecked": "2026-03-28T14:55:54.771923+00:00"
  },
  "179-2-20807": {
    "url": "https://www.jwpepper.com/mentre-il-cuculo-3166691/p",
    "label": "Buy Sheet Music",
    "source": "JW Pepper link",
    "lastChecked": "2026-03-28T14:55:44.720417+00:00"
  },
  "179-2-20809": {
    "url": "https://www.jwpepper.com/je-le-vous-dirai-1995869/p",
    "label": "Buy Sheet Music",
    "source": "JW Pepper link",
    "lastChecked": "2026-03-28T14:59:07.802102+00:00"
  },
  "179-2-20812": {
    "url": "https://www.jwpepper.com/el-grillo-10706977e/p",
    "label": "Buy Sheet Music",
    "source": "JW Pepper link",
    "lastChecked": "2026-03-28T14:54:38.994080+00:00"
  },
  "179-2-20816": {
    "url": "https://www.jwpepper.com/matona-lovely-maiden-342097/p",
    "label": "Buy Sheet Music",
    "source": "JW Pepper link",
    "lastChecked": "2026-03-28T14:55:19.238803+00:00"
  },
  "179-2-20818": {
    "url": "https://www.jwpepper.com/madrigal-morro-lasso-5008321/p",
    "label": "Buy Sheet Music",
    "source": "JW Pepper link",
    "lastChecked": "2026-03-28T14:59:08.572585+00:00"
  },
  "179-2-20822": {
    "url": "https://www.jwpepper.com/the-john-dowland-ayres-11214727f/p",
    "label": "Buy Sheet Music",
    "source": "JW Pepper link",
    "lastChecked": "2026-03-28T14:59:41.515941+00:00"
  },
  "179-2-20835": {
    "url": "https://www.jwpepper.com/farewell-3107174/p",
    "label": "Buy Sheet Music",
    "source": "JW Pepper link",
    "lastChecked": "2026-03-28T14:54:43.409131+00:00"
  },
  "179-2-20836": {
    "url": "https://www.jwpepper.com/ce-moys-de-may-5792197/p",
    "label": "Buy Sheet Music",
    "source": "JW Pepper link",
    "lastChecked": "2026-03-28T14:55:49.139764+00:00"
  },
  "179-2-20845": {
    "url": "https://www.jwpepper.com/and-the-green-grass-grew-3126752/p",
    "label": "Buy Sheet Music",
    "source": "JW Pepper link",
    "lastChecked": "2026-03-28T14:55:02.038773+00:00"
  },
  "179-2-20850": {
    "url": "https://www.jwpepper.com/two-morley-madrigals-for-men-10308715/p",
    "label": "Buy Sheet Music",
    "source": "JW Pepper link",
    "lastChecked": "2026-03-28T14:55:26.355834+00:00"
  },
  "179-2-20853": {
    "url": "https://www.jwpepper.com/o-sleep-fond-fancy-5080486/p",
    "label": "Buy Sheet Music",
    "source": "JW Pepper link",
    "lastChecked": "2026-03-28T14:56:08.082986+00:00"
  },
  "179-2-20858": {
    "url": "https://www.jwpepper.com/springtime-mantleth-every-bough-1361500/p",
    "label": "Buy Sheet Music",
    "source": "JW Pepper link",
    "lastChecked": "2026-03-28T14:59:38.596483+00:00"
  },
  "179-2-20861": {
    "url": "https://www.jwpepper.com/donde-hay-1354190/p",
    "label": "Buy Sheet Music",
    "source": "JW Pepper link",
    "lastChecked": "2026-03-28T14:55:28.129282+00:00"
  },
  "179-2-20872": {
    "url": "https://www.jwpepper.com/ein-hennlein-weiss-11201059/p",
    "label": "Buy Sheet Music",
    "source": "JW Pepper link",
    "lastChecked": "2026-03-28T14:55:57.206572+00:00"
  },
  "179-2-20875": {
    "url": "https://www.jwpepper.com/aupres-de-ma-blonde-4807517/p",
    "label": "Buy Sheet Music",
    "source": "JW Pepper link",
    "lastChecked": "2026-03-28T14:59:24.461831+00:00"
  },
  "179-2-20881": {
    "url": "https://www.jwpepper.com/the-oxford-book-of-english-madrigals-1481571/p",
    "label": "Buy Sheet Music",
    "source": "JW Pepper link",
    "lastChecked": "2026-03-28T14:59:24.204886+00:00"
  },
  "179-2-20887": {
    "url": "https://www.jwpepper.com/six-weelkes-madrigals-11409083/p",
    "label": "Buy Sheet Music",
    "source": "JW Pepper link",
    "lastChecked": "2026-03-28T14:59:29.606770+00:00"
  },
  "179-2-20889": {
    "url": "https://www.jwpepper.com/as-fair-as-morn-1207620/p",
    "label": "Buy Sheet Music",
    "source": "JW Pepper link",
    "lastChecked": "2026-03-28T14:55:29.155248+00:00"
  },
  "179-2-20892": {
    "url": "https://www.jwpepper.com/laughing-so-heartily-5081013/p",
    "label": "Buy Sheet Music",
    "source": "JW Pepper link",
    "lastChecked": "2026-03-28T14:59:03.994164+00:00"
  },
  "179-2-25069": {
    "url": "https://www.jwpepper.com/two-chansons-1994045/p",
    "label": "Buy Sheet Music",
    "source": "JW Pepper link",
    "lastChecked": "2026-03-28T14:55:38.572554+00:00"
  },
  "179-2-34230": {
    "url": "https://www.jwpepper.com/ay-linda-amiga-10616174/p",
    "label": "Buy Sheet Music",
    "source": "JW Pepper link",
    "lastChecked": "2026-03-28T14:54:10.220646+00:00"
  },
  "179-3-20899": {
    "url": "https://www.jwpepper.com/non-e-tempo-1277961/p",
    "label": "Buy Sheet Music",
    "source": "JW Pepper link",
    "lastChecked": "2026-03-28T14:54:22.503600+00:00"
  },
  "179-3-20906": {
    "url": "https://www.jwpepper.com/o-bella-fusa-10065314/p",
    "label": "Buy Sheet Music",
    "source": "JW Pepper link",
    "lastChecked": "2026-03-28T14:55:48.829893+00:00"
  },
  "179-3-20909": {
    "url": "https://www.jwpepper.com/tutto-lo-di-mi-dici-11576527f/p",
    "label": "Buy Sheet Music",
    "source": "JW Pepper link",
    "lastChecked": "2026-03-28T14:55:07.069125+00:00"
  },
  "179-3-20918": {
    "url": "https://www.jwpepper.com/18-songs-7388416/p",
    "label": "Buy Sheet Music",
    "source": "JW Pepper link",
    "lastChecked": "2026-03-28T14:59:44.583485+00:00"
  },
  "179-3-20928": {
    "url": "https://www.jwpepper.com/15-balletti-set-iii-5792312/p",
    "label": "Buy Sheet Music",
    "source": "JW Pepper link",
    "lastChecked": "2026-03-28T14:59:00.539916+00:00"
  },
  "179-3-20938": {
    "url": "https://www.jwpepper.com/two-morley-madrigals-for-men-10308715/p",
    "label": "Buy Sheet Music",
    "source": "JW Pepper link",
    "lastChecked": "2026-03-28T14:59:27.342888+00:00"
  },
  "179-3-20939": {
    "url": "https://www.jwpepper.com/two-morley-madrigals-for-men-10308715/p",
    "label": "Buy Sheet Music",
    "source": "JW Pepper link",
    "lastChecked": "2026-03-28T14:59:28.772284+00:00"
  },
  "179-3-20944": {
    "url": "https://www.jwpepper.com/in-these-delightful-pleasant-groves-340836/p",
    "label": "Buy Sheet Music",
    "source": "JW Pepper link",
    "lastChecked": "2026-03-28T14:59:37.677558+00:00"
  },
  "179-3-20949": {
    "url": "https://www.jwpepper.com/fa-una-canzona-1586098/p",
    "label": "Buy Sheet Music",
    "source": "JW Pepper link",
    "lastChecked": "2026-03-28T14:56:09.513622+00:00"
  },
  "179-3-20951": {
    "url": "https://www.jwpepper.com/six-weelkes-madrigals-11409083/p",
    "label": "Buy Sheet Music",
    "source": "JW Pepper link",
    "lastChecked": "2026-03-28T14:55:05.543089+00:00"
  },
  "179-3-20952": {
    "url": "https://www.jwpepper.com/european-madrigals-437947/p",
    "label": "Buy Sheet Music",
    "source": "JW Pepper link",
    "lastChecked": "2026-03-28T14:59:33.793089+00:00"
  },
  "179-3-20955": {
    "url": "https://www.jwpepper.com/the-oxford-book-of-english-madrigals-1481571/p",
    "label": "Buy Sheet Music",
    "source": "JW Pepper link",
    "lastChecked": "2026-03-28T14:55:19.254245+00:00"
  },
  "179-3-20958": {
    "url": "https://www.jwpepper.com/o-music-loveliest-art-4041653/p",
    "label": "Buy Sheet Music",
    "source": "JW Pepper link",
    "lastChecked": "2026-03-28T14:54:39.956367+00:00"
  },
  "179-3-23783": {
    "url": "https://www.jwpepper.com/madrigal-morro-lasso-5008321/p",
    "label": "Buy Sheet Music",
    "source": "JW Pepper link",
    "lastChecked": "2026-03-28T14:55:54.748896+00:00"
  },
  "179-3-34235": {
    "url": "https://www.jwpepper.com/madrigal-morro-lasso-5008321/p",
    "label": "Buy Sheet Music",
    "source": "JW Pepper link",
    "lastChecked": "2026-03-28T14:55:22.293686+00:00"
  },
  "179-3-34236": {
    "url": "https://www.jwpepper.com/tenebrae-factae-sunt-175869/p",
    "label": "Buy Sheet Music",
    "source": "JW Pepper link",
    "lastChecked": "2026-03-28T14:55:07.283052+00:00"
  }
}